odoo10_addon_purchase_order_analytic_search-10.0.1.0.0.99.dev2-py2.7-nspkg.pth
odoo/addons/purchase_order_analytic_search/README.rst
odoo/addons/purchase_order_analytic_search/__init__.py
odoo/addons/purchase_order_analytic_search/__manifest__.py
odoo/addons/purchase_order_analytic_search/i18n/purchase_order_analytic_search.pot
odoo/addons/purchase_order_analytic_search/models/__init__.py
odoo/addons/purchase_order_analytic_search/models/purchase_order.py
odoo/addons/purchase_order_analytic_search/static/description/icon.png
odoo/addons/purchase_order_analytic_search/tests/__init__.py
odoo/addons/purchase_order_analytic_search/tests/test_analytic_search.py
odoo/addons/purchase_order_analytic_search/views/purchase_order_view.xml
odoo10_addon_purchase_order_analytic_search-10.0.1.0.0.99.dev2.dist-info/DESCRIPTION.rst
odoo10_addon_purchase_order_analytic_search-10.0.1.0.0.99.dev2.dist-info/METADATA
odoo10_addon_purchase_order_analytic_search-10.0.1.0.0.99.dev2.dist-info/RECORD
odoo10_addon_purchase_order_analytic_search-10.0.1.0.0.99.dev2.dist-info/WHEEL
odoo10_addon_purchase_order_analytic_search-10.0.1.0.0.99.dev2.dist-info/metadata.json
odoo10_addon_purchase_order_analytic_search-10.0.1.0.0.99.dev2.dist-info/namespace_packages.txt
odoo10_addon_purchase_order_analytic_search-10.0.1.0.0.99.dev2.dist-info/top_level.txt
