Metadata-Version: 2.0
Name: odoo10-addon-purchase-order-analytic-search
Version: 10.0.1.0.0.99.dev2
Summary: Search purchase orders by analytic account. New menu entry in
Home-page: https://odoo-community.org/
Author: Eficent, Camptocamp, Odoo Community Association (OCA)
Author-email: support@odoo-community.org
License: LGPL-3
Platform: UNKNOWN
Classifier: Programming Language :: Python
Classifier: Framework :: Odoo
Classifier: License :: OSI Approved :: GNU Lesser General Public License v3 (LGPLv3)
Requires-Python: ~=2.7
Requires-Dist: odoo (<10.1dev,>=10.0)
